{
  "version": 1,
  "songs": {
    "EllJZsNjiCFALIDvHV46": {
      "slug": "misut-bursukai",
      "hash": "a0882cd2a1507d05"
    },
    "WPSl7AwHOIA1qgDvpm13": {
      "slug": "oyasumi-nakigoe-sayonara-utahime",
      "hash": "36d32baeeadb17ea"
    },
    "tNMBD6wIPdfbPAd3ByWj": {
      "slug": "daiji-na-koto",
      "hash": "a97f6a163ab1a073"
    },
    "3Dr0j3CZ4NKjtGWWyOfw": {
      "slug": "haru-ni-mau",
      "hash": "3fd1a6669577b8f1"
    },
    "GrHIieB60N5LThYgOV2l": {
      "slug": "shigatsu-no-ao",
      "hash": "41a642d80f2d07c4"
    },
    "vro2dGwnOBSAUvtKYPoh": {
      "slug": "renairon",
      "hash": "cc5cf561e537b4d4"
    },
    "UML4QszVhBBG5HzyttUx": {
      "slug": "yui-yui-no-uta",
      "hash": "be1d2cd5456c1e9f"
    },
    "lMLoJqXelBnVOws8MIf9": {
      "slug": "kimi-no-kawari",
      "hash": "87638ba8e41d7146"
    },
    "dVLDcBzozmMTVbrAET8F": {
      "slug": "kowai-hanashi",
      "hash": "954e05c48a896176"
    },
    "um3c2HVP5FqTGLCcBH3B": {
      "slug": "kotoba-no-tsuzuki",
      "hash": "2f8d8ce7727bbd46"
    },
    "DDIecOe0ryjpCNEtBju6": {
      "slug": "amanojaku",
      "hash": "85434c1a56b97f09"
    },
    "7vyphgRFQAY8aa2F6e5r": {
      "slug": "suiheisen",
      "hash": "5839d2d59e87a92e"
    },
    "qiHRmi2xDIrndLrSuz5p": {
      "slug": "pretender",
      "hash": "ca9792536d636b98"
    },
    "s6TCD3nl9JPabIXdEKwd": {
      "slug": "stay-with-me",
      "hash": "f64ec0a24704a721"
    },
    "2Rh57agsMapp1NHaaKzE": {
      "slug": "magnus",
      "hash": "678ea917746360a4"
    },
    "Ciocf0VXDCXAnaROsUso": {
      "slug": "yuigon",
      "hash": "82f30d30addb4be8"
    },
    "rdDrFsgkeEKl8CMsxxpT": {
      "slug": "kokoronashi",
      "hash": "2b33fa760980931d"
    },
    "GEHo9XOhQEq9hcPHznhI": {
      "slug": "eien-no-akuruhi",
      "hash": "e8dd53e8506a31d6"
    },
    "CgjiVBf03kkyerFdzT0f": {
      "slug": "spiral",
      "hash": "b7db85b7933d585c"
    },
    "pqhArPt67G7ymhKJZetk": {
      "slug": "watagashi",
      "hash": "3f9e2acfe3f5e535"
    },
    "49mzmJtuH0NglmFhXdis": {
      "slug": "fuyu-no-hanashi",
      "hash": "4951df0a54aa768e"
    },
    "Xko0SA7bpTbRZbTO13Nv": {
      "slug": "marigold",
      "hash": "1ab746200f309346"
    },
    "zQH1Ub0GpBqPpSVCXLb0": {
      "slug": "answer",
      "hash": "6bf907e9f158c144"
    },
    "r0RhO3pvQ9VsiZv4BOjZ": {
      "slug": "ano-yume-wo-nazotte",
      "hash": "e903c548c629699a"
    },
    "zOikamPoLkTQFBhFJEZc": {
      "slug": "fuyu-no-present",
      "hash": "a7e9bf6d15f8ca06"
    },
    "Ba466Tq3eT9ROzSCgFiK": {
      "slug": "sakura-koi",
      "hash": "b981833681ea0c89"
    },
    "GFxya5UHwvy14bBvBCIs": {
      "slug": "tabako",
      "hash": "ad4a4f6fac92cc76"
    },
    "9PNACbWnfZIzqRWzp1CH": {
      "slug": "sarishinohara",
      "hash": "a549469de912943e"
    },
    "Vwyht1zP2mesB8k6P20z": {
      "slug": "umi-he",
      "hash": "833120faf6b3fb17"
    },
    "MmPahpWdGGxvwgYwscMN": {
      "slug": "kimi-ni-saigo-no-kuchizuke-wo",
      "hash": "0eeacef96ead9523"
    },
    "lNsuhw4I3JFBclgcfH7Y": {
      "slug": "ikite-ita-nda-yo-na",
      "hash": "4f08e9cb2b0f1cdc"
    },
    "oCYYWnpia64ot8Vo9DkA": {
      "slug": "futaba",
      "hash": "3c169f81e5bcb9ee"
    },
    "dSkjszU7wtlnSZxGQvJo": {
      "slug": "muri-ni-warawanakute-ii-yo",
      "hash": "73db6927c4de2bc2"
    },
    "eEh0AGneBiYybd0BG4oz": {
      "slug": "one-room",
      "hash": "c053a6555fdc1b94"
    },
    "EOEUiPh5Bb8usptbtNIK": {
      "slug": "doushitemo-doushitemo",
      "hash": "2d7c4cd0e942735e"
    },
    "aalG74CYfFdmOAf8JGGL": {
      "slug": "kizuato",
      "hash": "cec05484aeeaad71"
    },
    "rNpkbbYdovz8DQpNELSv": {
      "slug": "bokura-dake-no-shudaika",
      "hash": "eb4e873e39168e19"
    },
    "ZBSjs1SZj6kRBvHQKGPb": {
      "slug": "marutsuke",
      "hash": "f246911dc354f50b"
    },
    "BvvS4JZw5zGvPaaCCyc2": {
      "slug": "uragawa-no-sonzai",
      "hash": "bce9d768f3d75668"
    },
    "fP4LywmbYD6Zkk22Vg5T": {
      "slug": "yoru-ga-akeru",
      "hash": "ccff23e4212818c6"
    },
    "1hm3KlKrm4Ej3CQ9Ku1Q": {
      "slug": "totte",
      "hash": "6e0a1084b374acb3"
    },
    "LsfwypunFuKMb0pYUZ4x": {
      "slug": "himawari",
      "hash": "f48f4257f10285ba"
    },
    "g8mxyj2RGpxsdiBaWG6Z": {
      "slug": "hikari-no-machi",
      "hash": "46bd73731752dc76"
    },
    "fUYIFVNERvLUWQ4cF5kF": {
      "slug": "hairaito",
      "hash": "4e73c620754d7088"
    },
    "L0xSxNg1uT3XwRQYto41": {
      "slug": "hoshi-ga-furu",
      "hash": "db9c92ba98074082"
    },
    "JxE6eXVxIge8TSRwN637": {
      "slug": "insomnia",
      "hash": "414d0a8d8527ba6c"
    },
    "Bg5xfgufKs2n6M9V9U8E": {
      "slug": "usseswa",
      "hash": "377767abb41f932d"
    },
    "Ry5Wt12s9sukp3YNF3y0": {
      "slug": "hyakka-ryouran",
      "hash": "00dd8677172259dd"
    },
    "RTzkD3FLvFSbPGXMcHrE": {
      "slug": "RTzkD3FLvFSbPGXMcHrE",
      "hash": "eb6b8971ac2ca7a9"
    },
    "YUmv5V7udvBhRJoIsry6": {
      "slug": "kurisumasu-songu",
      "hash": "f606a18a7e855afb"
    },
    "mFam4JeH2bsYcMdgSuKu": {
      "slug": "takane-no-hanako-san",
      "hash": "9d3fa1a5c0fee37a"
    },
    "WFzzGODB2gTsbyEe8YgX": {
      "slug": "happi-endo",
      "hash": "34fe63988f8898e6"
    },
    "VZ7HUADRb2L46yVhVPYW": {
      "slug": "mabataki",
      "hash": "e887248ab0e08f6e"
    },
    "N5cCh6h3Iz9LnA2h4YaF": {
      "slug": "awato-hitsuji",
      "hash": "181bb852b4a7d95e"
    },
    "TGoBuN5H0KELrNewLA90": {
      "slug": "hajimari-hajimari",
      "hash": "7e8a3421bac90d70"
    },
    "LWtNB6Dw6XKERuXjzIhG": {
      "slug": "tegami",
      "hash": "0f58acf7ff2cd764"
    },
    "IyQQWurZSlMt1PRHI9py": {
      "slug": "boku-no-kami-sama",
      "hash": "3b691cf30764f661"
    }
  }
}
